xls2moodle/__init__.py
xls2moodle/__main__.py
xls2moodle/_version.py
xls2moodle/xml_templates/four_correct.xml
xls2moodle/xml_templates/one_correct.xml
xls2moodle/xml_templates/template.xml
xls2moodle/xml_templates/three_correct.xml
xls2moodle/xml_templates/two_correct.xml
xls2moodle-1.12.dist-info/LICENSE
xls2moodle-1.12.dist-info/METADATA
xls2moodle-1.12.dist-info/WHEEL
xls2moodle-1.12.dist-info/entry_points.txt
xls2moodle-1.12.dist-info/top_level.txt
xls2moodle-1.12.dist-info/RECORD
