Metadata-Version: 2.1
Name: xls2moodle
Version: 1.12
Summary: xls2moodle: Import multiple-choice questions from excel to moodle.
Home-page: UNKNOWN
Author: Sven Giese
Author-email: sven.giese88@gmail.com
License: Apache License 2.0
Project-URL: Bug Tracker, https://github.com/gieses/xls2moodle/issues
Project-URL: Homepage, https://github.com/gieses/xls2moodle
Keywords: moodle,excel,multiple-choice,exam
Platform: UNKNOWN
Classifier: Programming Language :: Python
Classifier: Programming Language :: Python :: 3.8
Classifier: Programming Language :: Python :: Implementation :: PyPy
Requires-Python: >=3.6.0
Requires-Dist: lxml
Requires-Dist: pandas
Requires-Dist: numpy
Requires-Dist: xlrd
